MNNCV/__init__.py
MNNCV-0.1.12.dist-info/METADATA
MNNCV-0.1.12.dist-info/WHEEL
MNNCV-0.1.12.dist-info/top_level.txt
MNNCV-0.1.12.dist-info/RECORD
