Metadata-Version: 2.1
Name: MNNCV
Version: 0.1.12
Summary: MNNCV python sdk
Home-page: https://github.com/alibaba/MNN
Author: forkong
Author-email: UNKNOWN
License: UNKNOWN
Platform: many
Requires-Dist: Pillow
Requires-Dist: streamlit (>=0.55.2)
